{"Tops and Dresses":{"  0-2 ":{"Bust":["31.5"],"Hips":["33"],"Waist":["24.5"]},"  10 ":{"Bust":["37"],"Hips":["39.5"],"Waist":["30"]},"  14 ":{"Bust":["41"],"Hips":["43.5"],"Waist":["34.5"]},"  16 ":{"Bust":["43"],"Hips":["46"],"Waist":["37"]},"  24W ":{"Bust":["50.5"],"Hips":["54"],"Waist":["45.75"]},"  4 ":{"Bust":["33"],"Hips":["34.5"],"Waist":["25.5"]},"  6 ":{"Bust":["34"],"Hips":["36"],"Waist":["27"]},"  8 ":{"Bust":["35.5"],"Hips":["37.5"],"Waist":["28"]}," 12 ":{"Bust":["39"],"Hips":["41.5"],"Waist":["32"]}," 22W ":{"Bust":["48.5"],"Hips":["51.5"],"Waist":["43"]}," 26W ":{"Bust":["52.5"],"Hips":["56.75"],"Waist":["48.25"]},"18":{"Bust":["45"],"Hips":["48.5"],"Waist":["38.5"]},"L":{"Bust":["39","41"],"Hips":["41.5","43.5"],"Waist":["32","34.5"]},"M":{"Bust":["35.5","37"],"Hips":["37.5","39.5"],"Waist":["28","30"]},"S":{"Bust":["33","34"],"Hips":["34.5","36"],"Waist":["25.5","27"]},"XL":{"Bust":["43","45"],"Hips":["46","48.5"],"Waist":["37","38.5"]},"XS":{"Bust":["31.5"],"Hips":["33"],"Waist":["24.5"]},"XXL":{"Bust":["48.5","50.5"],"Hips":["51.5","54"],"Waist":["43","45.75"]},"XXXL":{"Bust":["52.5"],"Hips":["56.75"],"Waist":["48.25"]}}}